taijipid/__init__.py
taijipid/controller_adapter.cpython-310-x86_64-linux-gnu.so
taijipid/cstepres.cpython-310-x86_64-linux-gnu.so
taijipid/datacheck.cpython-310-x86_64-linux-gnu.so
taijipid/openresp.cpython-310-x86_64-linux-gnu.so
taijipid/pidcascalc.cpython-310-x86_64-linux-gnu.so
taijipid/pidconv.cpython-310-x86_64-linux-gnu.so
taijipid/pidid32_mimo.cpython-310-x86_64-linux-gnu.so
taijipid/pididsiso32.cpython-310-x86_64-linux-gnu.so
taijipid/pidoldresp.cpython-310-x86_64-linux-gnu.so
taijipid/pidresp2.cpython-310-x86_64-linux-gnu.so
taijipid/pidresp2_32.cpython-310-x86_64-linux-gnu.so
taijipid/pidresp2_ff.cpython-310-x86_64-linux-gnu.so
taijipid/pidresp2_mimo.cpython-310-x86_64-linux-gnu.so
taijipid/pidresp3.cpython-310-x86_64-linux-gnu.so
taijipid/pidtestsig.cpython-310-x86_64-linux-gnu.so
taijipid/pidtune.cpython-310-x86_64-linux-gnu.so
taijipid/pidtune_ff.cpython-310-x86_64-linux-gnu.so
taijipid/pidtune_mimo.cpython-310-x86_64-linux-gnu.so
taijipid/savemat.cpython-310-x86_64-linux-gnu.so
taijipid/simtime.cpython-310-x86_64-linux-gnu.so
taijipid/taijipid_warpper.cpython-310-x86_64-linux-gnu.so
taijipid/tools/__init__.py
taijipid/tools/datapre_on.cpython-310-x86_64-linux-gnu.so
taijipid/tools/datapre_pid.cpython-310-x86_64-linux-gnu.so
taijipid/tools/fastarx.cpython-310-x86_64-linux-gnu.so
taijipid/tools/fastarxini.cpython-310-x86_64-linux-gnu.so
taijipid/tools/fastarxm3ini.cpython-310-x86_64-linux-gnu.so
taijipid/tools/loord_on.cpython-310-x86_64-linux-gnu.so
taijipid/tools/lowordd2.cpython-310-x86_64-linux-gnu.so
taijipid/tools/mdrd_fr.cpython-310-x86_64-linux-gnu.so
taijipid/tools/piddelay.cpython-310-x86_64-linux-gnu.so
taijipid/tools/pidid.cp312-win_amd64.pyd
taijipid/tools/pidid.cpython-310-x86_64-linux-gnu.so
taijipid/tools/pidmdrd_mimo.cpython-310-x86_64-linux-gnu.so
taijipid/tools/prbs.cpython-310-x86_64-linux-gnu.so
taijipid/tools/siso_oe.cpython-310-x86_64-linux-gnu.so
taijipid-2.1.0.dist-info/METADATA
taijipid-2.1.0.dist-info/WHEEL
taijipid-2.1.0.dist-info/top_level.txt
taijipid-2.1.0.dist-info/RECORD
