Metadata-Version: 2.4
Name: taijipid
Version: 2.1.0
Summary: Tai-Ji PID tuning algorithm
Author-email: kkzhang <kkzhang3@hotmail.com>
Requires-Python: >=3.10
Requires-Dist: cython
Requires-Dist: numpy
Requires-Dist: scipy
Requires-Dist: matplotlib
Requires-Dist: taiji_hasp>=0.3.2
Requires-Dist: pycryptodome
Requires-Dist: tjcommon
